simd5/__init__.py
simd5-0.3.3.dist-info/METADATA
simd5-0.3.3.dist-info/WHEEL
simd5-0.3.3.dist-info/licenses/LICENSE
simd5-0.3.3.dist-info/RECORD
