Metadata-Version: 2.4
Name: simd5
Version: 0.3.3
Summary: Python module to create and check MD5 files for digital deliveries.
Project-URL: Homepage, https://github.com/Smithsonian/simd5
Project-URL: Bug Tracker, https://github.com/Smithsonian/simd5/issues
Author-email: "Luis J. Villanueva" <villanueval@si.edu>
License-File: LICENSE
Classifier: License :: OSI Approved :: Apache Software License
Classifier: Operating System :: OS Independent
Classifier: Programming Language :: Python :: 3
Requires-Python: >=3.6
Requires-Dist: p-tqdm
Requires-Dist: pandas
